planning_centric_metrics/__init__.py
planning_centric_metrics/__version__.py
planning_centric_metrics/models.py
planning_centric_metrics/planning_kl.py
planning_centric_metrics-0.0.8.dist-info/METADATA
planning_centric_metrics-0.0.8.dist-info/WHEEL
planning_centric_metrics-0.0.8.dist-info/top_level.txt
planning_centric_metrics-0.0.8.dist-info/RECORD
