Metadata-Version: 2.1
Name: planning-centric-metrics
Version: 0.0.8
Summary: API for computing "Planning KL-Divergence" (https://arxiv.org/abs/2004.08745)
Home-page: https://github.com/nv-tlabs/planning-centric-metrics
Author: Jonah Philion
Author-email: jonahphilion@gmail.com
License: Apache 2.0
Platform: UNKNOWN
Classifier: License :: OSI Approved :: MIT License
Classifier: Programming Language :: Python
Classifier: Programming Language :: Python :: 3
Classifier: Programming Language :: Python :: 3.6
Classifier: Programming Language :: Python :: Implementation :: PyPy
Requires-Python: >=3.6.0
Requires-Dist: torch (>=1.3.1)
Requires-Dist: ujson
Requires-Dist: numpy
Requires-Dist: matplotlib
Requires-Dist: opencv-python
Requires-Dist: pyquaternion
Requires-Dist: tqdm
Requires-Dist: torchvision (>=0.4.2)
